cofyflex/__init__.py
cofyflex/price_matrix/__init__.py
cofyflex-0.0.4.dist-info/LICENSE
cofyflex-0.0.4.dist-info/METADATA
cofyflex-0.0.4.dist-info/WHEEL
cofyflex-0.0.4.dist-info/top_level.txt
cofyflex-0.0.4.dist-info/RECORD
