Metadata-Version: 2.1
Name: cofyflex
Version: 0.0.4
Summary: COFYCloud Flexibility Microservices
Home-page: https://docs.cofybox.io
Author: Jan Pecinovsky
Author-email: jan@energieid.be
Project-URL: Bug Tracker, https://gitlab.com/rescoopvpp/cofycloud-flex-services/-/issues
Classifier: Programming Language :: Python :: 3
Classifier: License :: OSI Approved :: MIT License
Classifier: Operating System :: OS Independent
Requires-Python: >=3.6
License-File: LICENSE
Requires-Dist: pandas
